awssnap/__init__.py
awssnap/main.py
aws_snap-1.1.2.dist-info/LICENSE
aws_snap-1.1.2.dist-info/METADATA
aws_snap-1.1.2.dist-info/WHEEL
aws_snap-1.1.2.dist-info/entry_points.txt
aws_snap-1.1.2.dist-info/top_level.txt
aws_snap-1.1.2.dist-info/RECORD
