Metadata-Version: 2.1
Name: aws-snap
Version: 1.1.2
Summary: CLI (simple command line client) for making snapshots of AWS EC2 instances
Home-page: https://gitlab.com/shindagger/aws-snap-python
Author: Andy Klier
Author-email: andyklier@gmail.com
License: UNKNOWN
Platform: UNKNOWN
Classifier: Programming Language :: Python :: 3
Classifier: License :: OSI Approved :: MIT License
Classifier: Operating System :: OS Independent
Requires-Python: >=3.6
Requires-Dist: setuptools
Requires-Dist: string-color (>=0.2.7)
Requires-Dist: boto3
